a2a_adapter/__init__.py
a2a_adapter/adapter.py
a2a_adapter/client.py
a2a_adapter/loader.py
a2a_adapter/integrations/__init__.py
a2a_adapter/integrations/callable.py
a2a_adapter/integrations/crewai.py
a2a_adapter/integrations/langchain.py
a2a_adapter/integrations/n8n.py
a2a_adapter-0.1.3.dist-info/licenses/LICENSE
a2a_adapter-0.1.3.dist-info/METADATA
a2a_adapter-0.1.3.dist-info/WHEEL
a2a_adapter-0.1.3.dist-info/top_level.txt
a2a_adapter-0.1.3.dist-info/RECORD
