Metadata-Version: 2.4
Name: a2a-adapter
Version: 0.1.3
Summary: A2A Protocol Adapter SDK for integrating various agent frameworks
Author-email: HYBRO AI <info@hybro.ai>
License: Apache-2.0
Project-URL: Homepage, https://github.com/hybroai/a2a-adapter
Project-URL: Documentation, https://github.com/hybroai/a2a-adapter#readme
Project-URL: Repository, https://github.com/hybroai/a2a-adapter
Classifier: Development Status :: 3 - Alpha
Classifier: Intended Audience :: Developers
Classifier: License :: OSI Approved :: Apache Software License
Classifier: Programming Language :: Python :: 3
Classifier: Programming Language :: Python :: 3.11
Classifier: Programming Language :: Python :: 3.12
Classifier: Topic :: Software Development :: Libraries :: Python Modules
Requires-Python: >=3.11
License-File: LICENSE
Requires-Dist: a2a>=0.44.0
Requires-Dist: a2a-sdk[http-server]>=0.3.0
Requires-Dist: uvicorn>=0.27.0
Requires-Dist: httpx>=0.26.0
Requires-Dist: pydantic>=2.0.0
Provides-Extra: n8n
Provides-Extra: crewai
Requires-Dist: crewai>=0.1.0; extra == "crewai"
Provides-Extra: langchain
Requires-Dist: langchain>=0.1.0; extra == "langchain"
Requires-Dist: langchain-core>=0.1.0; extra == "langchain"
Provides-Extra: langgraph
Requires-Dist: langgraph>=0.0.1; extra == "langgraph"
Provides-Extra: all
Requires-Dist: crewai>=0.1.0; extra == "all"
Requires-Dist: langchain>=0.1.0; extra == "all"
Requires-Dist: langchain-core>=0.1.0; extra == "all"
Requires-Dist: langgraph>=0.0.1; extra == "all"
Provides-Extra: dev
Requires-Dist: pytest>=7.4.0; extra == "dev"
Requires-Dist: pytest-asyncio>=0.21.0; extra == "dev"
Requires-Dist: black>=23.0.0; extra == "dev"
Requires-Dist: ruff>=0.1.0; extra == "dev"
Requires-Dist: mypy>=1.0.0; extra == "dev"
Dynamic: license-file
